{"seats": [{"position": [550,484],"size": [45,18 ], "rowID": 1 },{"position": [709,480],"size": [74,30 ], "rowID": 1 },{"position": [145,429],"size": [80,32 ], "rowID": 2 },{"position": [335,427],"size": [74,30 ], "rowID": 2 },{"position": [614,422],"size": [75,30 ], "rowID": 3 },{"position": [705,421],"size": [69,28 ], "rowID": 3 },{"position": [795,419],"size": [75,30 ], "rowID": 3 },{"position": [272,385],"size": [71,28 ], "rowID": 4 },{"position": [598,386],"size": [71,28 ], "rowID": 4 },{"position": [763,385],"size": [69,27 ], "rowID": 4 },{"position": [273,339],"size": [72,29 ], "rowID": 5 },{"position": [356,337],"size": [70,28 ], "rowID": 5 },{"position": [598,335],"size": [66,26 ], "rowID": 5 },{"position": [759,332],"size": [69,28 ], "rowID": 5 },{"position": [733,270],"size": [61,24 ], "rowID": 6 },{"position": [450,212],"size": [64,26 ], "rowID": 7 },{"position": [708,208],"size": [64,26 ], "rowID": 8 },{"position": [957,207],"size": [65,26 ], "rowID": 8 },{"position": [463,172],"size": [45,18 ], "rowID": 9 },{"position": [991,164],"size": [41,17 ], "rowID": 10 },{"position": [411,132],"size": [48,19 ], "rowID": 11 },{"position": [470,133],"size": [40,16 ], "rowID": 11 },{"position": [421,98],"size": [42,17 ], "rowID": 12 },{"position": [616,98],"size": [47,19 ], "rowID": 12 },{"position": [962,93],"size": [43,17 ], "rowID": 13 },{"position": [382,72],"size": [40,16 ], "rowID": 14 },{"position": [519,71],"size": [40,16 ], "rowID": 15 },{"position": [563,71],"size": [44,18 ], "rowID": 15 },{"position": [475,48],"size": [41,17 ], "rowID": 16 },{"position": [519,48],"size": [38,15 ], "rowID": 16 },{"position": [605,48],"size": [38,15 ], "rowID": 16 },{"position": [389,47],"size": [42,17 ], "rowID": 17 },{"position": [562,47],"size": [38,15 ], "rowID": 17 },{"position": [559,28],"size": [38,15 ], "rowID": 18 },{"position": [780,4],"size": [37,15 ], "rowID": 19 }],
"size":[1280, 720]}
